exe/HTSC_FileSync.exe
pythonProject/__init__.py
pythonProject/main.py
insight_pythonsdk-0.0.1.dist-info/METADATA
insight_pythonsdk-0.0.1.dist-info/WHEEL
insight_pythonsdk-0.0.1.dist-info/top_level.txt
insight_pythonsdk-0.0.1.dist-info/RECORD
